plutoprint/py.typed
plutoprint/_plutoprint.cp312-win_amd64.dll.a
plutoprint/_plutoprint.cp312-win_amd64.pyd
plutoprint/__init__.py
plutoprint/__init__.pyi
plutoprint/__main__.py
plutoprint/fontconfig/fonts.conf
plutoprint/fontconfig/conf.d/10-hinting-slight.conf
plutoprint/fontconfig/conf.d/10-scale-bitmap-fonts.conf
plutoprint/fontconfig/conf.d/10-sub-pixel-none.conf
plutoprint/fontconfig/conf.d/10-yes-antialias.conf
plutoprint/fontconfig/conf.d/11-lcdfilter-default.conf
plutoprint/fontconfig/conf.d/20-unhint-small-vera.conf
plutoprint/fontconfig/conf.d/30-metric-aliases.conf
plutoprint/fontconfig/conf.d/40-nonlatin.conf
plutoprint/fontconfig/conf.d/45-generic.conf
plutoprint/fontconfig/conf.d/45-latin.conf
plutoprint/fontconfig/conf.d/48-spacing.conf
plutoprint/fontconfig/conf.d/49-sansserif.conf
plutoprint/fontconfig/conf.d/50-user.conf
plutoprint/fontconfig/conf.d/51-local.conf
plutoprint/fontconfig/conf.d/60-generic.conf
plutoprint/fontconfig/conf.d/60-latin.conf
plutoprint/fontconfig/conf.d/65-fonts-persian.conf
plutoprint/fontconfig/conf.d/65-nonlatin.conf
plutoprint/fontconfig/conf.d/69-unifont.conf
plutoprint/fontconfig/conf.d/70-no-bitmaps-except-emoji.conf
plutoprint/fontconfig/conf.d/80-delicious.conf
plutoprint/fontconfig/conf.d/90-synthetic.conf
plutoprint-0.16.0.dist-info/DELVEWHEEL
plutoprint-0.16.0.dist-info/entry_points.txt
plutoprint-0.16.0.dist-info/LICENSE
plutoprint-0.16.0.dist-info/METADATA
plutoprint-0.16.0.dist-info/RECORD
plutoprint-0.16.0.dist-info/WHEEL
plutoprint.libs/libplutobook-0-5b44e414f539813e76bbf40e4b3e4003.dll
