Metadata-Version: 2.1
Name: plutoprint
Version: 0.16.0
Summary: Paged HTML rendering library
Keywords: html,css,svg,pdf,png,html2pdf,html2png
Author-Email: Samuel Ugochukwu <sammycageagle@gmail.com>
License: MIT License
Classifier: Development Status :: 4 - Beta
Classifier: Intended Audience :: Developers
Classifier: License :: OSI Approved :: MIT License
Classifier: Operating System :: OS Independent
Classifier: Programming Language :: C
Classifier: Programming Language :: Python
Classifier: Programming Language :: Python :: 3.10
Classifier: Programming Language :: Python :: 3.11
Classifier: Programming Language :: Python :: 3.12
Classifier: Programming Language :: Python :: 3.13
Classifier: Programming Language :: Python :: 3.14
Classifier: Programming Language :: Python :: 3 :: Only
Classifier: Programming Language :: Python :: Implementation :: CPython
Classifier: Typing :: Typed
Classifier: Topic :: Multimedia :: Graphics :: Graphics Conversion
Classifier: Topic :: Multimedia :: Graphics :: Presentation
Classifier: Topic :: Printing
Classifier: Topic :: Text Processing :: Markup :: XML
Classifier: Topic :: Text Processing :: Markup :: HTML
Project-URL: Homepage, https://github.com/plutoprint
Project-URL: Documentation, https://plutoprint.readthedocs.io
Project-URL: Code, https://github.com/plutoprint/plutoprint
Project-URL: Issues, https://github.com/plutoprint/plutoprint/issues
Project-URL: Donation, https://github.com/sponsors/plutoprint
Requires-Python: >=3.10
Provides-Extra: test
Requires-Dist: pytest; extra == "test"
Requires-Dist: pytest-cov; extra == "test"
